brandintel/__init__.py
brandintel/core.py
brandintel-0.1.4.dist-info/licenses/LICENSE
brandintel-0.1.4.dist-info/METADATA
brandintel-0.1.4.dist-info/WHEEL
brandintel-0.1.4.dist-info/top_level.txt
brandintel-0.1.4.dist-info/RECORD
