Metadata-Version: 2.4
Name: brandintel
Version: 0.1.4
Summary: you are hackedd
Author: Khushi Choudhary
Author-email: khushichoudhary04@gmail.com
License: MIT
Classifier: Programming Language :: Python :: 3
Classifier: License :: OSI Approved :: MIT License
Classifier: Operating System :: OS Independent
Requires-Python: >=3.8
License-File: LICENSE
Requires-Dist: google-generativeai
Dynamic: license-file
